timestep/__init__.py
timestep/agents/__init__.py
timestep/agents/petting_zoo_agent/__init__.py
timestep/agents/petting_zoo_agent/agent.py
timestep_agents_petting_zoo_agent-0.1.0.dist-info/LICENSE
timestep_agents_petting_zoo_agent-0.1.0.dist-info/METADATA
timestep_agents_petting_zoo_agent-0.1.0.dist-info/WHEEL
timestep_agents_petting_zoo_agent-0.1.0.dist-info/RECORD
